setup.cfg
setup.py
apiary/__init__.py
apiary/__main__.py
apiary/cli.py
apiary/common.py
apiary.egg-info/PKG-INFO
apiary.egg-info/SOURCES.txt
apiary.egg-info/dependency_links.txt
apiary.egg-info/entry_points.txt
apiary.egg-info/requires.txt
apiary.egg-info/top_level.txt
apiary/command/__init__.py
apiary/command/preview.py
apiary/file_templates/__init__.py
apiary/file_templates/preview.py
apiary/helpers/__init__.py
apiary/helpers/javascript_helper.py