Metadata-Version: 1.1
Name: apiary
Version: 0.0.7
Summary: Python version of the Ruby Apiary client
Home-page: https://github.com/Jimflip/apiary-client.git
Author: James Birmingham, Apiary
Author-email: james@dimsum.tv
License: UNKNOWN
Download-URL: https://github.com/Jimflip/apiary-client/archive/0.0.7.tar.gz
Platform: UNKNOWN
